pydartdiags/__init__.py
pydartdiags/data.py
pydartdiags/matplots/__init__.py
pydartdiags/matplots/matplots.py
pydartdiags/obs_sequence/__init__.py
pydartdiags/obs_sequence/composite_types.yaml
pydartdiags/obs_sequence/obs_sequence.py
pydartdiags/plots/__init__.py
pydartdiags/plots/plots.py
pydartdiags/stats/__init__.py
pydartdiags/stats/stats.py
pydartdiags-0.6.3.dist-info/licenses/LICENSE
pydartdiags-0.6.3.dist-info/METADATA
pydartdiags-0.6.3.dist-info/WHEEL
pydartdiags-0.6.3.dist-info/top_level.txt
pydartdiags-0.6.3.dist-info/RECORD
