Metadata-Version: 2.4
Name: pydartdiags
Version: 0.6.3
Summary: Observation Sequence Diagnostics for DART
Author-email: Helen Kershaw <hkershaw@ucar.edu>
License-Expression: Apache-2.0
Project-URL: Homepage, https://github.com/NCAR/pyDARTdiags.git
Project-URL: Issues, https://github.com/NCAR/pyDARTdiags/issues
Project-URL: Documentation, https://ncar.github.io/pyDARTdiags
Classifier: Programming Language :: Python :: 3
Classifier: Operating System :: OS Independent
Requires-Python: >=3.8
License-File: LICENSE
Requires-Dist: pandas>=2.2.0
Requires-Dist: numpy>=1.26
Requires-Dist: plotly>=5.22.0
Requires-Dist: pyyaml>=6.0.2
Requires-Dist: matplotlib>=3.9.4
Dynamic: license-file
